LICENSE.txt
MANIFEST.in
README.txt
__init__.py
example2.py
example__pystaggrelite3.py
pystaggrelite3.py
setup.py
test__pystaggrelite3.py
dist/pystaggrelite3-0.1.2/__init__.py
dist/pystaggrelite3-0.1.2/example__pystaggrelite3.py
dist/pystaggrelite3-0.1.2/pystaggrelite3.py
dist/pystaggrelite3-0.1.2/setup.py
dist/pystaggrelite3-0.1.2/test__pystaggrelite3 - Copy.py
dist/pystaggrelite3-0.1.2/test__pystaggrelite3.py
dist/pystaggrelite3-0.1.2/build/lib/pystaggrelite3.py
dist/pystaggrelite3-0.1.2/dist/pystaggrelite3-0.1.2/__init__.py
dist/pystaggrelite3-0.1.2/dist/pystaggrelite3-0.1.2/example__pystaggrelite3.py
dist/pystaggrelite3-0.1.2/dist/pystaggrelite3-0.1.2/pystaggrelite3.py
dist/pystaggrelite3-0.1.2/dist/pystaggrelite3-0.1.2/setup.py
dist/pystaggrelite3-0.1.2/dist/pystaggrelite3-0.1.2/test__pystaggrelite3 - Copy.py
dist/pystaggrelite3-0.1.2/dist/pystaggrelite3-0.1.2/test__pystaggrelite3.py
dist/pystaggrelite3-0.1.2/dist/pystaggrelite3-0.1.2/build/lib/pystaggrelite3.py
dist/pystaggrelite3-0.1.2/dist/pystaggrelite3-0.1.2/perf_comparisons/madis_statistics.py
dist/pystaggrelite3-0.1.2/dist/pystaggrelite3-0.1.2/perf_comparisons/timeit__comparisons.py
dist/pystaggrelite3-0.1.2/perf_comparisons/madis_statistics.py
dist/pystaggrelite3-0.1.2/perf_comparisons/timeit__comparisons.py
perf_comparisons/madis_statistics.py
perf_comparisons/timeit__comparisons.py
pystaggrelite3.egg-info/PKG-INFO
pystaggrelite3.egg-info/SOURCES.txt
pystaggrelite3.egg-info/dependency_links.txt
pystaggrelite3.egg-info/top_level.txt